pylibdmtx/__init__.py
pylibdmtx/dmtx_library.py
pylibdmtx/libdmtx-LICENSE.txt
pylibdmtx/pylibdmtx.py
pylibdmtx/pylibdmtx_error.py
pylibdmtx/wrapper.py
pylibdmtx/scripts/__init__.py
pylibdmtx/scripts/read_datamatrix.py
pylibdmtx/scripts/write_datamatrix.py
pylibdmtx/tests/__init__.py
pylibdmtx/tests/datamatrix.png
pylibdmtx/tests/empty.png
pylibdmtx/tests/test_dmtx_library.py
pylibdmtx/tests/test_pylibdmtx.py
pylibdmtx/tests/test_read_write_datamatrix.py
pylibdmtx_gs1grader-0.1.11.data/scripts/read_datamatrix.py
pylibdmtx_gs1grader-0.1.11.data/scripts/write_datamatrix.py
pylibdmtx_gs1grader-0.1.11.dist-info/LICENSE.txt
pylibdmtx_gs1grader-0.1.11.dist-info/METADATA
pylibdmtx_gs1grader-0.1.11.dist-info/WHEEL
pylibdmtx_gs1grader-0.1.11.dist-info/entry_points.txt
pylibdmtx_gs1grader-0.1.11.dist-info/top_level.txt
pylibdmtx_gs1grader-0.1.11.dist-info/RECORD
