Metadata-Version: 2.1
Name: pylibdmtx-gs1grader
Version: 0.1.11
Summary: Fork of NaturalHistoryMuseum pylibdmtx with GS1 extensions
Home-page: https://github.com/Ceyeborg/pylibdmtx
Author: Ceyeb.org(Forked from NaturalHistoryMuseum)
Author-email: info@ceyeb.org
License: MIT
Project-URL: Original Project, https://github.com/NaturalHistoryMuseum/pylibdmtx/
Project-URL: Forked Project, https://github.com/Ceyeborg/pylibdmtx
Classifier: Development Status :: 4 - Beta
Classifier: License :: OSI Approved :: MIT License
Classifier: Topic :: Utilities
Classifier: Programming Language :: Python :: 2
Classifier: Programming Language :: Python :: 2.7
Classifier: Programming Language :: Python :: 3
Classifier: Programming Language :: Python :: 3.5
Classifier: Programming Language :: Python :: 3.6
Classifier: Programming Language :: Python :: 3.7
Classifier: Programming Language :: Python :: 3.8
Classifier: Programming Language :: Python :: 3.9
Classifier: Programming Language :: Python :: 3.10
License-File: LICENSE.txt
Requires-Dist: enum34>=1.1.6; python_version == "2.7"
Requires-Dist: pathlib>=1.0.1; python_version == "2.7"
Provides-Extra: scripts
Requires-Dist: Pillow>=3.2.0; extra == "scripts"
